{"cameraMode":{"drawMode":0,"name":"Shaded","section":"Shading Mode"},"sceneLighting":false,"audioPlay":false,"sceneViewState":{"m_AlwaysRefresh":false,"showFog":true,"showSkybox":false,"showFlares":true,"showImageEffects":true,"showParticleSystems":true,"showVisualEffectGraphs":true,"m_FxEnabled":true},"in2DMode":false,"pivot":{"x":-0.46782639622688296,"y":7.243866443634033,"z":-2.749840021133423},"rotation":{"x":-0.5483660101890564,"y":0.02686215378344059,"z":-0.017549196258187295,"w":-0.8354965448379517},"size":7.089217185974121,"orthographic":false}